awscreds/__init__.py
awscreds/awscreds
awscreds-0.1.0.data/scripts/awscreds
awscreds-0.1.0.dist-info/LICENSE
awscreds-0.1.0.dist-info/METADATA
awscreds-0.1.0.dist-info/WHEEL
awscreds-0.1.0.dist-info/top_level.txt
awscreds-0.1.0.dist-info/RECORD
