Metadata-Version: 2.1
Name: awscreds
Version: 0.1.0
Summary: awscreds stores AWS credentials in OS's secure storage
Home-page: https://github.com/DmitriyLyalyuev/awscreds
Author: Dmitriy Lyalyuev
Author-email: dmitriy@lyalyuev.info
License: MIT
Keywords: ssh aws devops sysadmin
Platform: UNKNOWN
Classifier: Environment :: MacOS X
Classifier: Environment :: Console
Classifier: Intended Audience :: Developers
Classifier: Intended Audience :: System Administrators
Classifier: License :: OSI Approved :: MIT License
Classifier: Natural Language :: English
Classifier: Programming Language :: Python :: 3
Classifier: Programming Language :: Python :: 3.5
Classifier: Programming Language :: Python :: 3.6
Classifier: Programming Language :: Python :: 3.7
Classifier: Topic :: System :: Systems Administration
Classifier: Topic :: Utilities
Requires-Dist: keyring
